contract_nli/VERSION
contract_nli/__init__.py
contract_nli/config.yaml
contract_nli/main.py
contract_nli/predict.py
contract_nli/train.py
contract_nli/config/__init__.py
contract_nli/config/core.py
contract_nli/data/__init__.py
contract_nli/model/__init__.py
contract_nli/model/aggregate.py
contract_nli/model/attend.py
contract_nli/model/compare.py
contract_nli/model/decomposable_attention.py
contract_nli/model/mlp.py
contract_nli/preprocessing/__init__.py
contract_nli/preprocessing/data_management.py
contract_nli/preprocessing/snli_dataset.py
contract_nli/trained_model/__init__.py
contract_nli/trained_model/model.pth
contract_nli/trained_model/vocab.pth
contract_nli-1.0.7.dist-info/METADATA
contract_nli-1.0.7.dist-info/WHEEL
contract_nli-1.0.7.dist-info/top_level.txt
contract_nli-1.0.7.dist-info/RECORD
